cjm_fasthtml_workflow_transcription_single_file/__init__.py
cjm_fasthtml_workflow_transcription_single_file/_modidx.py
cjm_fasthtml_workflow_transcription_single_file/components/__init__.py
cjm_fasthtml_workflow_transcription_single_file/components/processor.py
cjm_fasthtml_workflow_transcription_single_file/components/results.py
cjm_fasthtml_workflow_transcription_single_file/components/steps.py
cjm_fasthtml_workflow_transcription_single_file/core/__init__.py
cjm_fasthtml_workflow_transcription_single_file/core/adapters.py
cjm_fasthtml_workflow_transcription_single_file/core/config.py
cjm_fasthtml_workflow_transcription_single_file/core/html_ids.py
cjm_fasthtml_workflow_transcription_single_file/core/job_tracker.py
cjm_fasthtml_workflow_transcription_single_file/core/protocols.py
cjm_fasthtml_workflow_transcription_single_file/settings/__init__.py
cjm_fasthtml_workflow_transcription_single_file/settings/components.py
cjm_fasthtml_workflow_transcription_single_file/settings/schemas.py
cjm_fasthtml_workflow_transcription_single_file/storage/__init__.py
cjm_fasthtml_workflow_transcription_single_file/storage/config.py
cjm_fasthtml_workflow_transcription_single_file/storage/file_storage.py
cjm_fasthtml_workflow_transcription_single_file/storage/protocols.py
cjm_fasthtml_workflow_transcription_single_file/workflow/__init__.py
cjm_fasthtml_workflow_transcription_single_file/workflow/job_handler.py
cjm_fasthtml_workflow_transcription_single_file/workflow/routes.py
cjm_fasthtml_workflow_transcription_single_file/workflow/workflow.py
cjm_fasthtml_workflow_transcription_single_file-0.0.21.dist-info/licenses/LICENSE
cjm_fasthtml_workflow_transcription_single_file-0.0.21.dist-info/METADATA
cjm_fasthtml_workflow_transcription_single_file-0.0.21.dist-info/WHEEL
cjm_fasthtml_workflow_transcription_single_file-0.0.21.dist-info/entry_points.txt
cjm_fasthtml_workflow_transcription_single_file-0.0.21.dist-info/top_level.txt
cjm_fasthtml_workflow_transcription_single_file-0.0.21.dist-info/RECORD
