Metadata-Version: 2.4
Name: cjm-fasthtml-workflow-transcription-single-file
Version: 0.0.21
Summary: A self-contained single-file transcription workflow for FastHTML applications.
Home-page: https://github.com/cj-mills/cjm-fasthtml-workflow-transcription-single-file
Author: Christian J. Mills
Author-email: 9126128+cj-mills@users.noreply.github.com
License: Apache Software License 2.0
Keywords: nbdev jupyter notebook python
Classifier: Development Status :: 4 - Beta
Classifier: Intended Audience :: Developers
Classifier: Natural Language :: English
Classifier: Programming Language :: Python :: 3.12
Classifier: License :: OSI Approved :: Apache Software License
Requires-Python: >=3.12
License-File: LICENSE
Requires-Dist: fastcore
Requires-Dist: python-fasthtml
Requires-Dist: cjm-fasthtml-app-core
Requires-Dist: cjm-fasthtml-daisyui
Requires-Dist: cjm-fasthtml-tailwind
Requires-Dist: cjm-fasthtml-interactions
Requires-Dist: cjm-fasthtml-settings
Requires-Dist: cjm-fasthtml-sse
Requires-Dist: cjm-fasthtml-jsonschema
Requires-Dist: cjm-plugin-system
Requires-Dist: cjm-transcription-plugin-system
Requires-Dist: cjm_fasthtml_file_browser
Provides-Extra: dev
Dynamic: author
Dynamic: author-email
Dynamic: classifier
Dynamic: description
Dynamic: description-content-type
Dynamic: home-page
Dynamic: keywords
Dynamic: license
Dynamic: license-file
Dynamic: provides-extra
Dynamic: requires-dist
Dynamic: requires-python
Dynamic: summary
